nbstripout/__init__.py
nbstripout/__main__.py
nbstripout/_nbstripout.py
nbstripout/_utils.py
nbstripout-0.9.0.dist-info/licenses/LICENSE.txt
nbstripout-0.9.0.dist-info/METADATA
nbstripout-0.9.0.dist-info/WHEEL
nbstripout-0.9.0.dist-info/entry_points.txt
nbstripout-0.9.0.dist-info/top_level.txt
nbstripout-0.9.0.dist-info/RECORD
