Metadata-Version: 2.4
Name: nbstripout
Version: 0.9.0
Summary: Strips outputs from Jupyter and IPython notebooks
Author-email: Florian Rathgeber <florian.rathgeber@gmail.com>
Maintainer-email: Florian Rathgeber <florian.rathgeber@gmail.com>
License-Expression: MIT
Project-URL: Homepage, https://pypi.org/project/nbstripout
Project-URL: Repository, https://github.com/kynan/nbstripout
Keywords: jupyter,notebook,ipython,git,filter,hooks
Classifier: Development Status :: 4 - Beta
Classifier: Environment :: Console
Classifier: Framework :: IPython
Classifier: Framework :: Jupyter
Classifier: Intended Audience :: Developers
Classifier: Operating System :: MacOS
Classifier: Operating System :: Microsoft :: Windows
Classifier: Operating System :: POSIX :: Linux
Classifier: Programming Language :: Python
Classifier: Programming Language :: Python :: 3
Classifier: Programming Language :: Python :: 3.10
Classifier: Programming Language :: Python :: 3.11
Classifier: Programming Language :: Python :: 3.12
Classifier: Programming Language :: Python :: 3.13
Classifier: Programming Language :: Python :: 3.14
Classifier: Topic :: Software Development :: Version Control
Requires-Python: >=3.10
License-File: LICENSE.txt
Requires-Dist: nbformat
Dynamic: license-file
